afdko-4.0.3.data/scripts/makeotfexe
afdko-4.0.3.data/scripts/rotatefont
afdko-4.0.3.data/scripts/sfntedit
afdko-4.0.3.data/scripts/sfntdiff
afdko-4.0.3.data/scripts/spot
afdko-4.0.3.data/scripts/detype1
afdko-4.0.3.data/scripts/mergefonts
afdko-4.0.3.data/scripts/type1
afdko-4.0.3.data/scripts/tx
afdko-4.0.3.dist-info/WHEEL
afdko-4.0.3.dist-info/entry_points.txt
afdko-4.0.3.dist-info/top_level.txt
afdko-4.0.3.dist-info/METADATA
afdko-4.0.3.dist-info/RECORD
afdko-4.0.3.dist-info/licenses/LICENSE.md
afdko/agd.py
afdko/otc2otf.py
afdko/ttxn.py
afdko/proofpdf.py
afdko/checkoutlinesufo.py
afdko/makeinstancesufo.py
afdko/ttfcomponentizer.py
afdko/ttfdecomponentizer.py
afdko/ufotools.py
afdko/otf2ttf.py
afdko/fdkutils.py
afdko/comparefamily.py
afdko/otf2otc.py
afdko/buildcff2vf.py
afdko/makeotf.py
afdko/convertfonttocid.py
afdko/buildmasterotfs.py
afdko/__init__.py
afdko/resources/AGD.txt
afdko/resources/Adobe-Japan1/83pv-RKSJ-H
afdko/resources/Adobe-Japan1/UniJIS2004-UTF32-H
afdko/resources/Adobe-Japan1/Adobe-Japan1_sequences.txt
afdko/resources/Adobe-CNS1/UniCNS-UTF32-H
afdko/resources/Adobe-CNS1/B5pc-H
afdko/resources/Adobe-CNS1/Adobe-CNS1_sequences.txt
afdko/resources/Adobe-GB1/GBpc-EUC-H
afdko/resources/Adobe-GB1/Adobe-GB1_sequences.txt
afdko/resources/Adobe-GB1/UniGB-UTF32-H
afdko/resources/Adobe-Korea1/UniKS-UTF32-H
afdko/resources/Adobe-Korea1/KSCpc-EUC-H
afdko/resources/Adobe-Korea1/Adobe-Korea1_sequences.txt
afdko/otfautohint/fdTools.py
afdko/otfautohint/autohint.py
afdko/otfautohint/glyphData.py
afdko/otfautohint/overlap.py
afdko/otfautohint/ufoFont.py
afdko/otfautohint/hintstate.py
afdko/otfautohint/report.py
afdko/otfautohint/splitpsdicts.py
afdko/otfautohint/hinter.py
afdko/otfautohint/logging.py
afdko/otfautohint/__main__.py
afdko/otfautohint/__init__.py
afdko/otfautohint/otfFont.py
afdko/pdflib/pdfutils.py
afdko/pdflib/pdfdoc.py
afdko/pdflib/otfpdf.py
afdko/pdflib/fontpdf.py
afdko/pdflib/pdfgeom.py
afdko/pdflib/pdfgen.py
afdko/pdflib/ttfpdf.py
afdko/pdflib/pdfmetrics.py
