Metadata-Version: 2.4
Name: afdko
Version: 4.0.3
Summary: Adobe Font Development Kit for OpenType
Home-page: https://github.com/adobe-type-tools/afdko
Author: Adobe Type team & friends
Author-email: afdko@adobe.com
License: Apache License, Version 2.0
Keywords: font development tools
Platform: macosx-10.9-x86_64
Classifier: Development Status :: 5 - Production/Stable
Classifier: Intended Audience :: Developers
Classifier: Topic :: Software Development :: Build Tools
Classifier: License :: OSI Approved :: Apache Software License
Classifier: Programming Language :: Python :: 3.9
Classifier: Operating System :: MacOS :: MacOS X
Classifier: Operating System :: Microsoft :: Windows
Classifier: Operating System :: POSIX :: Linux
Requires-Python: >=3.9
License-File: LICENSE.md
Requires-Dist: lxml>=4.9.3
Requires-Dist: booleanOperations>=0.9.0
Requires-Dist: defcon[lxml,pens]>=0.10.3
Requires-Dist: fontMath>=0.9.4
Requires-Dist: fontTools[lxml,ufo,unicode,woff]>=4.56.0
Requires-Dist: tqdm>=4.66.1
Requires-Dist: ufonormalizer>=0.6.2
Requires-Dist: ufoProcessor>=1.13.1
Dynamic: author
Dynamic: author-email
Dynamic: classifier
Dynamic: description
Dynamic: description-content-type
Dynamic: home-page
Dynamic: keywords
Dynamic: license
Dynamic: license-file
Dynamic: platform
Dynamic: requires-dist
Dynamic: requires-python
Dynamic: summary
